rf_api_client/__init__.py
rf_api_client/log.py
rf_api_client/rf_api_client.py
rf_api_client/utils.py
rf_api_client/api/__init__.py
rf_api_client/api/base_api.py
rf_api_client/api/comments_api.py
rf_api_client/api/files_api.py
rf_api_client/api/maps_api.py
rf_api_client/api/node_types_api.py
rf_api_client/api/nodes_api.py
rf_api_client/api/notify_api.py
rf_api_client/api/tags_api.py
rf_api_client/api/users_api.py
rf_api_client/models/__init__.py
rf_api_client/models/base_model.py
rf_api_client/models/comments_api_models.py
rf_api_client/models/files_api_models.py
rf_api_client/models/maps_api_models.py
rf_api_client/models/node_types_api_models.py
rf_api_client/models/nodes_api_models.py
rf_api_client/models/notify_models.py
rf_api_client/models/search_hit.py
rf_api_client/models/tags_api_models.py
rf_api_client/models/users_api_models.py
tests/__init__.py
tests/conftest.py
tests/parse_test.py
tests/prepare_map.py
tests/test_map.py
tests/test_search_nodes.py
rf_api_client-0.1.11.dist-info/LICENSE
rf_api_client-0.1.11.dist-info/METADATA
rf_api_client-0.1.11.dist-info/WHEEL
rf_api_client-0.1.11.dist-info/top_level.txt
rf_api_client-0.1.11.dist-info/RECORD
